LICENSE
README.md
setup.py
rust_python_fibonacci/__init__.py
rust_python_fibonacci.egg-info/PKG-INFO
rust_python_fibonacci.egg-info/SOURCES.txt
rust_python_fibonacci.egg-info/dependency_links.txt
rust_python_fibonacci.egg-info/entry_points.txt
rust_python_fibonacci.egg-info/requires.txt
rust_python_fibonacci.egg-info/top_level.txt
rust_python_fibonacci/cmd/__init__.py
rust_python_fibonacci/cmd/fib_numb.py
rust_python_fibonacci/fib_calcs/__init__.py
rust_python_fibonacci/fib_calcs/fib_number.py
rust_python_fibonacci/fib_calcs/fib_numbers.py
tests/rust_python_fibonacci/__init__.py
tests/rust_python_fibonacci/fib_calcs/__init__.py
tests/rust_python_fibonacci/fib_calcs/test_fib_number.py
tests/rust_python_fibonacci/fib_calcs/test_fib_numbers.py