Metadata-Version: 2.1
Name: rust-python-fibonacci
Version: 0.0.2
Summary: Calculates a Fibonacci number
Home-page: https://github.com/SportyGeek2015/rust_python_fibonacci
Author: SportyGeek2015
Author-email: this_is_not_a_real_emall_address@hotmail.com
Classifier: Development Status :: 4 - Beta
Classifier: Programming Language :: Python :: 3
Classifier: Operating System :: OS Independent
Requires-Python: >=3.10
Provides-Extra: server
License-File: LICENSE
